t9ek80/__init__.py
t9ek80/t9ek80.py
t9ek80-1.4.1.dist-info/LICENSE
t9ek80-1.4.1.dist-info/METADATA
t9ek80-1.4.1.dist-info/WHEEL
t9ek80-1.4.1.dist-info/top_level.txt
t9ek80-1.4.1.dist-info/RECORD
