Metadata-Version: 2.1
Name: t9ek80
Version: 1.4.1
Summary: Simrad EK80 Echosounder interface module.
Home-page: https://github.com/The1only/ek80/src
Author: Terje Nilsen
Author-email: terje.nilsen@km.kongsberg.com
License: UNKNOWN
Platform: UNKNOWN
Classifier: Programming Language :: Python :: 3
Classifier: License :: OSI Approved :: MIT License
Classifier: Operating System :: OS Independent
